gepref_text/__init__.py
gepref_text/base.py
gepref_text/filtering.py
gepref_text/normalization.py
gepref_text/py.typed
gepref_text/regex_sub.py
gepref_text/tokenization.py
gepref_text-0.1.5.dist-info/LICENSE
gepref_text-0.1.5.dist-info/WHEEL
gepref_text-0.1.5.dist-info/METADATA
gepref_text-0.1.5.dist-info/RECORD
