Metadata-Version: 2.1
Name: gepref_text
Version: 0.1.5
Summary: GEneral PREprocessing Framework for TEXT (gepref_text)
Author-email: Juan Lara <julara@unal.edu.co>
Requires-Python: >3.10
Requires-Dist: gepref==0.1.1
Requires-Dist: unidecode==1.3.8
Requires-Dist: nltk==3.8.1
Requires-Dist: pydantic==2.6.4
Requires-Dist: jedi-language-server ; extra == "dev"
Requires-Dist: mypy ; extra == "dev"
Requires-Dist: pytest ; extra == "dev"
Requires-Dist: ruff ; extra == "dev"
Requires-Dist: flit ; extra == "dev"
Requires-Dist: sphinx ; extra == "dev"
Requires-Dist: sphinx-book-theme ; extra == "dev"
Requires-Dist: myst_parser ; extra == "dev"
Provides-Extra: dev
